ntlog/__init__.py
ntlog/main.py
ntlog/ntlog.py
ntlog-1.1.dist-info/entry_points.txt
ntlog-1.1.dist-info/licenses/LICENSE
ntlog-1.1.dist-info/WHEEL
ntlog-1.1.dist-info/METADATA
ntlog-1.1.dist-info/RECORD
