Metadata-Version: 2.4
Name: ntlog
Version: 1.1
Summary: Append a log file to an running NestedText log
Keywords: nestedtext,logging
Author: Ken Kundert
Requires-Python: >=3.6
Classifier: Development Status :: 5 - Production/Stable
Classifier: Intended Audience :: Developers
Classifier: License :: OSI Approved :: MIT License
Classifier: Natural Language :: English
Classifier: Operating System :: POSIX :: Linux
Classifier: Programming Language :: Python :: 3
Classifier: Topic :: Utilities
License-File: LICENSE
Requires-Dist: arrow>=0.15
Requires-Dist: docopt
Requires-Dist: inform>=1.28
Requires-Dist: nestedtext
Requires-Dist: quantiphy
Project-URL: changelog, https://github.com/KenKundert/ntlog/blob/master/CHANGELOG.rst
Project-URL: documentation, https://github.com/KenKundert/ntlog/blob/master/README.rst
Project-URL: homepage, https://github.com/kenkundert/ntlog
Project-URL: repository, https://github.com/kenkundert/ntlog
